flask_debugtoolbar_flamegraph/__init__.py
flask_debugtoolbar_flamegraph/flamegraph.pl
flask_debugtoolbar_flamegraph/flamegraph.py
flask_debugtoolbar_flamegraph/flask_debugtoolbar_flamegraph.py
flask_debugtoolbar_flamegraph-0.1.2.dist-info/DESCRIPTION.rst
flask_debugtoolbar_flamegraph-0.1.2.dist-info/METADATA
flask_debugtoolbar_flamegraph-0.1.2.dist-info/RECORD
flask_debugtoolbar_flamegraph-0.1.2.dist-info/WHEEL
flask_debugtoolbar_flamegraph-0.1.2.dist-info/metadata.json
flask_debugtoolbar_flamegraph-0.1.2.dist-info/top_level.txt
