Metadata-Version: 2.0
Name: flask-debugtoolbar-flamegraph
Version: 0.1.2
Summary: Flamegraphs for Flask Debug Toolbar
Home-page: https://github.com/quantus/flask-debugtoolbar-flamegraph
Author: Pekka Pöyry
Author-email: pekka.poyry@gmail.com
License: MIT
Keywords: flask_debugtoolbar_flamegraph
Platform: UNKNOWN
Classifier: Development Status :: 4 - Beta
Classifier: Intended Audience :: Developers
Classifier: Natural Language :: English
Classifier: Programming Language :: Python :: 2
Classifier: Programming Language :: Python :: 2.7
Classifier: Programming Language :: Python :: 3
Classifier: Programming Language :: Python :: 3.4
